mordormail/EmailContentClass.py
mordormail/__init__.py
mordormail/send_email.py
mordormail-0.1.3.dist-info/LICENSE
mordormail-0.1.3.dist-info/METADATA
mordormail-0.1.3.dist-info/WHEEL
mordormail-0.1.3.dist-info/RECORD
