Metadata-Version: 2.1
Name: mordormail
Version: 0.1.3
Summary: A utility class to easily send templated emails from within python scripts.
Home-page: https://github.com/computational-ms/mordormail
Author: Tim Hudelmaier
Requires-Python: >=3.8
Classifier: Programming Language :: Python :: 3
Classifier: Programming Language :: Python :: 3.8
Classifier: Programming Language :: Python :: 3.9
Classifier: Programming Language :: Python :: 3.10
Classifier: Programming Language :: Python :: 3.11
Classifier: Programming Language :: Python :: 3.12
Requires-Dist: jinja2 (>=3.1.2,<4.0.0)
Project-URL: Repository, https://github.com/computational-ms/mordormail
